ifunnel/__init__.py
ifunnel/settings.py
ifunnel/financial_data/all_etfs_rets.parquet.gzip
ifunnel/financial_data/top_2000_etfs.xlsx
ifunnel/financial_data_preprocessing/__init__.py
ifunnel/financial_data_preprocessing/clean_downloaded_data.py
ifunnel/financial_data_preprocessing/get_algostrata_data.py
ifunnel/financial_data_preprocessing/get_yahoo_data.py
ifunnel/models/__init__.py
ifunnel/models/clustering.py
ifunnel/models/cvar_model.py
ifunnel/models/cvar_targets.py
ifunnel/models/data_analyser.py
ifunnel/models/main.py
ifunnel/models/mst.py
ifunnel/models/mvo_model.py
ifunnel/models/mvo_targets.py
ifunnel/models/scenario_generation.py
ifunnel/models/lifecycle/__init__.py
ifunnel/models/lifecycle/glide_path_creator.py
ifunnel/models/lifecycle/mvo_lifecycle_model.py
ifunnel-0.1.0.dist-info/METADATA
ifunnel-0.1.0.dist-info/WHEEL
ifunnel-0.1.0.dist-info/licenses/LICENSE
ifunnel-0.1.0.dist-info/RECORD
