Metadata-Version: 2.4
Name: ifunnel
Version: 0.1.0
Summary: Backend for the investment-funnel
Project-URL: repository, https://github.com/tschm/funnel
Author-email: Thomas Schmelzer <thomas.schmelzer@gmail.com>, Petr Vanek <abc@gmail.com>
License-File: LICENSE
Requires-Python: >=3.10
Requires-Dist: clarabel>=0.10.0
Requires-Dist: cvxpy-base>=1.6.1
Requires-Dist: loguru>=0.7.3
Requires-Dist: matplotlib>=3.10.0
Requires-Dist: mosek>=11.0.8
Requires-Dist: networkx>=3.4.2
Requires-Dist: numpy>=2.2.3
Requires-Dist: pandas>=2.2.3
Requires-Dist: plotly>=6.0.0
Requires-Dist: pyarrow>=19.0.1
Requires-Dist: pydantic-settings>=2.8.0
Requires-Dist: python-dateutil>=2.9.0.post0
Requires-Dist: python-dotenv>=1.1.1
Requires-Dist: requests>=2.32.3
Requires-Dist: scikit-learn>=1.6.1
Requires-Dist: scipy>=1.15.2
Requires-Dist: yfinance>=0.2.54
Provides-Extra: dev
Requires-Dist: pre-commit>=4.0.1; extra == 'dev'
Requires-Dist: pytest-cov>=6.0.0; extra == 'dev'
Requires-Dist: pytest>=8.3.3; extra == 'dev'
